ccs_digitalmarketplace_utils-79.13.0.dist-info/licenses/LICENCE
dmutils/__init__.py
dmutils/access_control.py
dmutils/asset_fingerprint.py
dmutils/authentication.py
dmutils/central_digital_platform_mocking.py
dmutils/cloudfoundry.py
dmutils/compliance_communications.py
dmutils/config.py
dmutils/cookie_probe.py
dmutils/csv_generator.py
dmutils/cyber_essentials.py
dmutils/dates.py
dmutils/deprecation.py
dmutils/dmp_so_status.py
dmutils/documents.py
dmutils/env_helpers.py
dmutils/external.py
dmutils/feature_flag.py
dmutils/filters.py
dmutils/flask.py
dmutils/flask_init.py
dmutils/formats.py
dmutils/fvra.py
dmutils/jinja2_environment.py
dmutils/logging.py
dmutils/lot_questions_utils.py
dmutils/ods.py
dmutils/proxy_fix.py
dmutils/py.typed
dmutils/request_id.py
dmutils/s3.py
dmutils/service_attribute.py
dmutils/session.py
dmutils/status.py
dmutils/timing.py
dmutils/urls.py
dmutils/user.py
dmutils/views.py
dmutils/email/__init__.py
dmutils/email/dm_mailchimp.py
dmutils/email/dm_notify.py
dmutils/email/exceptions.py
dmutils/email/helpers.py
dmutils/email/tokens.py
dmutils/email/user_account_email.py
dmutils/errors/__init__.py
dmutils/errors/api.py
dmutils/errors/frontend.py
dmutils/forms/__init__.py
dmutils/forms/compliance_communications.py
dmutils/forms/errors.py
dmutils/forms/fields.py
dmutils/forms/filters.py
dmutils/forms/helpers.py
dmutils/forms/mixins.py
dmutils/forms/validators.py
dmutils/forms/widgets.py
dmutils/govuk_country_register/__init__.py
dmutils/govuk_country_register/country.csv
dmutils/govuk_country_register/country.json
dmutils/govuk_country_register/country.py
dmutils/govuk_country_register/register.py
dmutils/presenters/__init__.py
dmutils/presenters/compliance_communications.py
dmutils/presenters/helpers.py
dmutils/presenters/kaminari_pagination.py
dmutils/presenters/pagination.py
dmutils/repoutils/__init__.py
dmutils/view_helpers/__init__.py
dmutils/view_helpers/compliance_communications.py
dmutils/view_helpers/frameworks.py
dmutils/view_helpers/pagination.py
dmutils/view_helpers/services.py
ccs_digitalmarketplace_utils-79.13.0.dist-info/METADATA
ccs_digitalmarketplace_utils-79.13.0.dist-info/WHEEL
ccs_digitalmarketplace_utils-79.13.0.dist-info/top_level.txt
ccs_digitalmarketplace_utils-79.13.0.dist-info/RECORD
