Metadata-Version: 2.4
Name: ccs-digitalmarketplace-utils
Version: 79.13.0
Summary: Common utils for Digital Marketplace apps.
Author: GDS Developers, CCS Developers
Project-URL: Homepage, https://github.com/Crown-Commercial-Service/ccs-digitalmarketplace-utils
Project-URL: Repository, https://github.com/Crown-Commercial-Service/ccs-digitalmarketplace-utils.git
Project-URL: Issues, https://github.com/Crown-Commercial-Service/ccs-digitalmarketplace-utils/issues
Project-URL: Changelog, https://github.com/Crown-Commercial-Service/ccs-digitalmarketplace-utils/CHANGELOG.md
Requires-Python: <3.15,>=3.11
License-File: LICENCE
Requires-Dist: Flask-WTF>=1.2.1
Requires-Dist: Flask<3.2,>=3.0
Requires-Dist: Flask-gzip>=0.2
Requires-Dist: Flask-Login>=0.6.3
Requires-Dist: Flask-Session<0.9.0,>=0.6.0
Requires-Dist: boto3<2,>=1.7.83
Requires-Dist: contextlib2>=21.6.0
Requires-Dist: cryptography>=41.0.4
Requires-Dist: ccs-digitalmarketplace-apiclient>=37.4.1
Requires-Dist: mailchimp3==3.0.21
Requires-Dist: requests<3,>=2.22.0
Requires-Dist: redis>=5.0.1
Requires-Dist: filetype<2,>=1.2.0
Requires-Dist: notifications-python-client<11.0.0,>=8.1.0
Requires-Dist: odfpy>=1.4.1
Requires-Dist: python-json-logger<5.0.0,>=4.0.0
Requires-Dist: pytz
Requires-Dist: unicodecsv>=0.14.1
Requires-Dist: urllib3<3
Requires-Dist: werkzeug<3.2,>=3.0
Requires-Dist: workdays>=1.4
Provides-Extra: dev
Requires-Dist: flake8==7.3.0; extra == "dev"
Requires-Dist: freezegun==1.5.5; extra == "dev"
Requires-Dist: hypothesis==6.148.7; extra == "dev"
Requires-Dist: moto==5.1.18; extra == "dev"
Requires-Dist: mypy==1.19.1; extra == "dev"
Requires-Dist: pytest==9.0.2; extra == "dev"
Requires-Dist: pytest-cov==7.0.0; extra == "dev"
Requires-Dist: pytest-datadir==1.8.0; extra == "dev"
Requires-Dist: requests-mock==1.12.1; extra == "dev"
Requires-Dist: testfixtures==10.0.0; extra == "dev"
Requires-Dist: ccs-digitalmarketplace-test-utils==7.6.0; extra == "dev"
Requires-Dist: types-python-dateutil; extra == "dev"
Requires-Dist: types-pytz; extra == "dev"
Requires-Dist: types-redis; extra == "dev"
Requires-Dist: types-requests; extra == "dev"
Requires-Dist: pre-commit==4.5.1; extra == "dev"
Dynamic: license-file
